oauth2_proxy/__init__.py
oauth2_proxy/app.py
oauth2_proxy-1.0.11.dist-info/DESCRIPTION.rst
oauth2_proxy-1.0.11.dist-info/METADATA
oauth2_proxy-1.0.11.dist-info/RECORD
oauth2_proxy-1.0.11.dist-info/WHEEL
oauth2_proxy-1.0.11.dist-info/metadata.json
oauth2_proxy-1.0.11.dist-info/top_level.txt
