Metadata-Version: 2.0
Name: oauth2-proxy
Version: 1.0.11
Summary: OAuth2 proxy with authorization/redirect flow
Home-page: https://github.com/zalando-stups/oauth2-proxy
Author: Zalando SE
Author-email: UNKNOWN
License: Apache License Version 2.0
Keywords: oauth flask proxy serve
Platform: UNKNOWN
Classifier: Programming Language :: Python
Classifier: Programming Language :: Python :: 3.4
Classifier: Development Status :: 4 - Beta
Classifier: Intended Audience :: Developers
Classifier: Operating System :: OS Independent
Requires-Dist: Flask
Requires-Dist: Flask-OAuthlib
Requires-Dist: requests
